{
    "course_id": "BAA00021",
    "course_name": "Thể dục 1",
    "course_start_page": 71,
    "course_end_page": 72,
    "content": "ĐỀ CƯƠNG TÓM TẮT \nBAA00021  - Thể dục 1  \n \n Thông tin chung  \n− Mã học phần  : BAA00021  \n− Khối kiến thức: Bắt buộc  - Đại cương  \n− Số tín chỉ: 2  \n• Lý thuyết  : 15 \n• Thực hành  : 30 \n• Bài tập  : 0 \n− Học phần học trước  :    \n Mô tả học phần  \nMôn học này giúp cho sinh viên có những kiến thức cơ bản về lợi ích, vai trò của việc tập luyện \nTDTT, cũng như  có khả năn g vận dụng những tri thức và kỷ năng vận động vào việc tự tập \nluyện hàng ngày để giữ gìn và nâng cao sức khỏe, phòng chống bệnh tật cho bản thân.  \n Mục tiêu của học phần  \nSau khoá học, sinh viên có khả năng:  \n− Hiểu rõ lợi ích của  việc tập luyện TDTT đối với sự phát triển của cơ thể và vai trò của \nGDTC trong mục tiêu phát triển con người toàn diện.  \n− Hiểu rõ tác dụng và có thể thực hiện tốt các kỹ thuật cơ bản của môn bóng chuyền, vận \ndụng tốt trong rèn luyện thân thể và thi đấu phong trào.  \n Nội dung học phần   \n Tài nguyên học phần  \nGiáo trình  \n− A.G.Airianx, Iu.N.Klesep (1997), Bóng chuyền, Nxb Thể dục Thể thao, Hà Nội.  \n− Bộ Đại học và Trung học chuyên nghiệp (1980), Tài liệu giảng dạy Thể dục thể thao. \nTập 1,2,3, Nxb Đại học và Trung học chuyên nghiệp, Hà Nội.  \n− Bùi Huy C hâm, Hà Mạnh Thư (1989), Chiến thuật bóng chuyền, Nxb Thể dục Thể \nthao, Hà Nội.  \n− R.Hedeman (2000), Sinh lý thể thao cho mọi người, Nxb Thể dục Thể thao, Hà Nội.   \n 72 Tài liệu tham khảo  \n− www.fivb.org  \n− https://volleyball.vn/  \nCông cụ hỗ trợ  \n− Sân, lưới bóng chuyền  \n− 20 quả bóng chuyền  "
}