{
    "course_id": "MTH00050",
    "course_name": "Toán học tổ hợp",
    "course_start_page": 59,
    "course_end_page": 61,
    "content": "ĐỀ CƯƠNG TÓM TẮT \nMTH00050  – Toán h ọc tổ hợp \n \n Thông tin chung  \n− Mã học phần  : MTH00050  \n− Tên tiếng Anh  : Combinatorial Mathematics  \n− Khối kiến thức: Bắt buộc  – Đại cương  \n− Số tín chỉ: 4  \n• Lý thuyết  : 45 \n• Thực hành  : 30 \n• Bài tập  : 0 \n− Học phần học trước  : Toán rời rạc, Nhập môn lập trình   \n Mô tả học phần  \nMôn học cung cấp cho sinh viên một số kiến thức về lý thuyết đồ thị, một số bài toán liên quan \ntới đồ thị,  tổ hợp, hàm sinh, nguyên lý bù trừ và các số đếm nâng cao. Các kiến thức của môn \nhọc là nền tảng cho các môn học chuyên ngành.  \n Mục tiêu của học phần  \nSau khoá học, sinh viên có khả năng:  \n− Hiểu các khái niệm của đồ thị và vận dụng giải quyết số bài toán cơ bản của đồ thị.  \n− Áp dụng các thuật toán đã học để giải quyết một số bài toán liên qu an đến cây  \n− Hiểu và giải quyết được một số bài toán về đường đi trên đồ thị  \n− Vận dụng lý thuyết tổ hợp để giải quyết một số bài toán đếm  \n− Xây dựng hàm sinh và vận dụng chúng để giải một số bài toán đếm  \n− Áp dụng nguyên lý bù trừ và đa thức quân xe vào một số bà i toán đếm  \n− Nắm vững định nghĩa của một số đếm nâng cao  \n Nội dung học phần   \nChương 1. Đại cương về đồ thị  \n1.1 Giới thiệu  \n1.2 Các khái niệm cơ bản  \n1.3 Biểu diễn đồ thị  \n1.4 Đẳng cấu đồ thị   \n 60 1.5 Đường đi, chu trình  \nChương 2. Cây  \n2.1 Định nghĩa và tính chất  \n2.2 Cây khung ngắn nhất  \n2.3 Cây có gốc  \n2.4 Phép duyệt cây  \nChương 3. Các bài toàn về đường đi  \n3.1 Đường đi ngắn nhất  \n3.2 Đồ thị Euler  \n3.3 Đồ thị Hamilton  \nChương 4. Tổ hợp cơ bản  \n4.1 Các nguyên lý đếm  \n4.2 Tổ hợp  \n4.3 Tổ hợp lặp \nChương 5. Hàm sinh  \n5.1 Định nghĩa hàm sinh  \n5.2 Hệ số hàm sinh  \n5.3 Phân hoạch số nguyên  \n5.4 Hàm sinh mũ  \nKiểm tra giữa kỳ  \n5.5 Phương pháp tổng  \n5.6 Giải hệ thức đệ quy bằng hàm sinh  \nChương 6. Nguyên lý bù trừ  \n6.1 Sơ đồ Ven  \n6.2 Nguyên lý bù trừ  \n6.3 Đa thức quân xe  \nChương 7. Số đếm nâng cao  \n7.1 Số Catalan  \n7.2 Số Stirling loại 2  \n7.3 Số Bell  \nÔn tập  \n Tài nguyên học phần  \nGiáo trình  \n− Alan Tucker, Applied Combinatorics 6th edition, JohnWiley & Sons, Inc.  \n− Trần Ngọc Danh, Toán rời rạc nâng cao, NXB ĐHQG -TPHCM, 20 01 \nTài liệu tham khảo  \n− Walter D. Wallis, John C. George, Introduction to Combinatorics, 2nd Edition, \nChapman and Hall/CRC, 2017  \n− Dương Anh Đức, Trần Đan Thư, Lý thuyết đồ thị, NXB ĐHQG -TPHCM, 2008  \n− K. Rosen, Discrete Mathematics and its Applications, 7th Edi tion, McGraw -Hill, 2011  \nCông cụ hỗ trợ  \n− Phần mềm Maple   \n 61  "
}